{
   "data": [
      {
         "datetime": "2024-10-03 11:30:20.642967",
         "stream": {
            "title": "Nico Guthmann",
            "channel_url": "https://www.youtube.com/@NicoGuthmann"
         },
         "stream_key": "Nico Guthmann",
         "live_id": null,
         "live_title": null,
         "last_video_id": "a6leaUYtqZE",
         "last_video_title": "CÓMO SERÁ el GOBIERNO DE JAVIER MILEI en ARGENTINA",
         "id": 277835498672365003
      },
      {
         "datetime": "2024-10-03 11:30:21.183291",
         "stream": {
            "title": "BLENDER",
            "channel_url": "https://www.youtube.com/@estoesblender"
         },
         "stream_key": "BLENDER",
         "live_id": "I-ch2Wun4Cg",
         "live_title": "DESAYUNO INTERMITENTE EN VIVO con Fede Simonetti, Elisa Sánchez, Mauro Szeta, Vale y Jove | BLENDER",
         "last_video_id": "NxqrERNCGxc",
         "last_video_title": "TODO sobre EL JOKER 2 con FIO SARGENTI | HAY ALGO AHÍ | BLENDER",
         "id": 533985333570939783
      },
      {
         "datetime": "2024-10-03 11:30:21.829264",
         "stream": {
            "title": "Radio con vos",
            "channel_url": "https://www.youtube.com/@RadioConVos89.9"
         },
         "stream_key": "Radio con vos",
         "live_id": "HcwnxhsZ5qo",
         "live_title": "YAQPA con Ernesto Tenembaum | RADIO CON VOS",
         "last_video_id": "9SdogOFvSUQ",
         "last_video_title": "Santiago Spaltro sobre el masivo apagón que afectó a zona sur y parte de la Ciudad",
         "id": 272479996852536616
      },
      {
         "datetime": "2024-10-03 11:30:22.435907",
         "stream": {
            "title": "Gelatina",
            "channel_url": "https://www.youtube.com/@SomosGelatina"
         },
         "stream_key": "Gelatina",
         "live_id": null,
         "live_title": null,
         "last_video_id": "8rjsjuXP3oQ",
         "last_video_title": "SEBASTIÁN TEYSERA: “QUEREMOS VOLVER A DONDE FUIMOS FELICES” | INDUSTRIA NACIONAL CON PEDRO ROSEMBLAT",
         "id": 259244651430329710
      },
      {
         "datetime": "2024-10-03 11:30:22.913727",
         "stream": {
            "title": "Futurock FM",
            "channel_url": "https://www.youtube.com/@futurock"
         },
         "stream_key": "Futurock FM",
         "live_id": null,
         "live_title": null,
         "last_video_id": "1iC-oDHNRjs",
         "last_video_title": "\"LOS PERIODISTAS DE FÚTBOL SON TODOS MENTIROSOS Y ENSOBRADOS\" | EL DUKA en DESPUÉS DE LA TORMENTA",
         "id": 233692808435034581
      },
      {
         "datetime": "2024-10-03 11:30:23.409779",
         "stream": {
            "title": "posdata",
            "channel_url": "https://www.youtube.com/@Posdata_ar"
         },
         "stream_key": "posdata",
         "live_id": null,
         "live_title": null,
         "last_video_id": "vC9KfYWPZNU",
         "last_video_title": "GRUPOS de AMIGUES | 3 EMPANADAS | @Posdata_ar",
         "id": 191591078776014768
      },
      {
         "datetime": "2024-10-03 11:30:23.854330",
         "stream": {
            "title": "Cenital",
            "channel_url": "https://www.youtube.com/@Cenitalcom"
         },
         "stream_key": "Cenital",
         "live_id": null,
         "live_title": null,
         "last_video_id": "t9becLI218o",
         "last_video_title": "LA COCINA DE CENITAL |  Encuentro con Mejores Amigos en el estudio y #OnTheRecord en vivo.",
         "id": 306584204639824864
      },
      {
         "datetime": "2024-10-03 11:30:24.520082",
         "stream": {
            "title": "Factoria 1251",
            "channel_url": "https://www.youtube.com/@factoria1251"
         },
         "stream_key": "Factoria 1251",
         "live_id": null,
         "live_title": null,
         "last_video_id": "0BpLzYJKKM0",
         "last_video_title": "ENTREVISTA a PABLO FERREYRA / #LoDijeoLoPensé?",
         "id": 185862609823161714
      },
      {
         "datetime": "2024-10-03 11:30:24.989339",
         "stream": {
            "title": "OLGA",
            "channel_url": "https://www.youtube.com/@olgaenvivo_"
         },
         "stream_key": "OLGA",
         "live_id": "zKb6y-X3Qis",
         "live_title": "SERÍA INCREÍBLE en OLGA con Nati Jota, Damián Betular, Grego Rossello y Homero Pettinato | EN VIVO",
         "last_video_id": "NikGG8qDee4",
         "last_video_title": "KARINA FT LAS NONAS y la COLUMNA de MOMO | Se Extraña a la Nona | COMPLETO 2/10",
         "id": 811783917407851447
      },
      {
         "datetime": "2024-10-03 11:30:25.585422",
         "stream": {
            "title": "LUZU TV",
            "channel_url": "https://www.youtube.com/@luzutv"
         },
         "stream_key": "LUZU TV",
         "live_id": "sfBa33WsxdE",
         "live_title": "ANTES QUE NADIE con DIEGO LEUCO, MICA VÁZQUEZ, YOYI FRANCELLA Y EL TRINCHE | EN VIVO",
         "last_video_id": "nfHH-SmMWWI",
         "last_video_title": "#STREAMMASTER l MARTIN GARABAL VIVE EN LUZU Y EL CURRO OCULTO DE PACHU",
         "id": 125021193912916677
      },
      {
         "datetime": "2024-10-03 11:30:25.989996",
         "stream": {
            "title": "Picnoc Extraterrestre",
            "channel_url": "https://www.youtube.com/@Picnic.Extraterrestre"
         },
         "stream_key": "Picnoc Extraterrestre",
         "live_id": null,
         "live_title": null,
         "last_video_id": "OITBGLy-rOE",
         "last_video_title": "SERGIO ROTMAN CON FABIÁN CASAS | PICNIC EXTRATERRESTRE 27.9 | PROGRAMA COMPLETO",
         "id": 748184283104638709
      },
      {
         "datetime": "2024-10-03 11:30:26.449393",
         "stream": {
            "title": "Pais de Boludos",
            "channel_url": "https://www.youtube.com/@PaisDeBoludos"
         },
         "stream_key": "Pais de Boludos",
         "live_id": null,
         "live_title": null,
         "last_video_id": "6Xnill5DfAo",
         "last_video_title": "PAÍS DE BOLUDOS | Y TODO A MEDIA LUZ + JUAN MAQUIEYRA | PDB",
         "id": 838481804820745772
      },
      {
         "datetime": "2024-10-03 11:30:26.906649",
         "stream": {
            "title": "Peroncho Delivery",
            "channel_url": "https://www.youtube.com/@PeronchoStandUp"
         },
         "stream_key": "Peroncho Delivery",
         "live_id": null,
         "live_title": null,
         "last_video_id": "-B5lC5GQN6w",
         "last_video_title": "Marcha histórica en defensa de las universidades. Mal día para el doctor horroris causa.",
         "id": 153341262012569137
      },
      {
         "datetime": "2024-10-03 11:30:27.528620",
         "stream": {
            "title": "Mate",
            "channel_url": "https://www.youtube.com/@somosmatear"
         },
         "stream_key": "Mate",
         "live_id": null,
         "live_title": null,
         "last_video_id": "IvHMaXKDTro",
         "last_video_title": "MERCEDES D’ALESSANDRO ANALIZA EL PRESUPUESTO 2025 DE JAVIER MILEI CON IVANA SZERMAN | MATE",
         "id": 145635594759461996
      },
      {
         "datetime": "2024-10-03 11:30:28.110953",
         "stream": {
            "title": "El Destape",
            "channel_url": "https://www.youtube.com/@ElDestapeTV"
         },
         "stream_key": "El Destape",
         "live_id": "XRF4kpSExaE",
         "live_title": "MASIVA MARCHA UNIVERSITARIA - HABRÁ CONSECUENCIAS EN VIVO CON ARI LIJALAD | El Destape",
         "last_video_id": "Jhj8ajRc4nY",
         "last_video_title": "VALE LA PENA | Editorial de Ari Lijalad",
         "id": 794690838869899042
      },
      {
         "datetime": "2024-10-03 11:30:28.489539",
         "stream": {
            "title": "Mano a Mano",
            "channel_url": "https://www.youtube.com/@ManoaMano-jz7up"
         },
         "stream_key": "Mano a Mano",
         "live_id": null,
         "live_title": null,
         "last_video_id": "I5hfOTNESuM",
         "last_video_title": "CUÁL ES EL JUEGO DE CRISTINA. Pablo Ibáñez y Alfredo Zaiat.",
         "id": 294030542011554402
      },
      {
         "datetime": "2024-10-03 11:30:28.900011",
         "stream": {
            "title": "220 Podcast",
            "channel_url": "https://www.youtube.com/@220Podcast"
         },
         "stream_key": "220 Podcast",
         "live_id": null,
         "live_title": null,
         "last_video_id": "xgt1I_SVZeE",
         "last_video_title": "ESPECIAL MARCHA UNIVERSITARIA",
         "id": 285922738951067278
      },
      {
         "datetime": "2024-10-03 11:30:29.288198",
         "stream": {
            "title": "Eva TV",
            "channel_url": "https://www.youtube.com/@evaenvivo"
         },
         "stream_key": "Eva TV",
         "live_id": null,
         "live_title": null,
         "last_video_id": "i8c0aA7eD48",
         "last_video_title": "JUAN DOE SANTIAGUEÑO? FEDERALISMO, COMUNICACIÓN Y POLÍTICA | Con la tuia en EVA TV",
         "id": 858554869569070528
      },
      {
         "datetime": "2024-10-03 11:30:29.937621",
         "stream": {
            "title": "Urbana Play",
            "channel_url": "https://www.youtube.com/@UrbanaPlayFM"
         },
         "stream_key": "Urbana Play",
         "live_id": null,
         "live_title": null,
         "last_video_id": "xJNoNv4zHpQ",
         "last_video_title": "Editorial de María O'Donnell: Argumentos de Milei para vetar la ley de financiamiento universitario",
         "id": 109570434836997627
      },
      {
         "datetime": "2024-10-03 11:30:30.410318",
         "stream": {
            "title": "Bondi Live",
            "channel_url": "https://www.youtube.com/@Bondi_liveok"
         },
         "stream_key": "Bondi Live",
         "live_id": null,
         "live_title": null,
         "last_video_id": "qh816yG9l34",
         "last_video_title": "MODA, TENDENCIAS Y ACTUALIDAD | ANGEL RESPONDE 02/10",
         "id": 914347398944020630
      },
      {
         "datetime": "2024-10-03 11:30:30.851273",
         "stream": {
            "title": "Vorterix",
            "channel_url": "https://www.youtube.com/@VorterixOficial"
         },
         "stream_key": "Vorterix",
         "live_id": "I4EKyW-Q1Os",
         "live_title": "🔴 MALDICION, VA A SER UN DIA HERMOSO con Mario Pergolini, Dani, El Polaco y Sebas | VORTERIX EN VIVO",
         "last_video_id": "o3PBTp3RGbk",
         "last_video_title": "LAS MEJORES GUITARRAS GAMERS | #QUEROMPIMOS Completo - 02/10 | Vorterix",
         "id": 215192781492265808
      },
      {
         "datetime": "2024-10-03 11:30:31.270653",
         "stream": {
            "title": "Neura Media",
            "channel_url": "https://www.youtube.com/@NeuraMedia"
         },
         "stream_key": "Neura Media",
         "live_id": null,
         "live_title": null,
         "last_video_id": "yinbf1yQZ0I",
         "last_video_title": "Gonzalo Garcés: Partes de la Verdad | Con Andrés Hatum (escritor) y Luciana Vázquez (periodista)",
         "id": 340215558713671423
      },
      {
         "datetime": "2024-10-03 11:30:31.888357",
         "stream": {
            "title": "RepublicaZ",
            "channel_url": "https://www.youtube.com/@republicaz"
         },
         "stream_key": "RepublicaZ",
         "live_id": null,
         "live_title": null,
         "last_video_id": "3FIcxLPkjx0",
         "last_video_title": "Se Picó | ¡NUEVAS NOVEDADES PARA el CASTING de GRAN HERMANO! + FUERTE CRUCE de ROMI y FLOR CABRERA",
         "id": 182946194775217940
      },
      {
         "datetime": "2024-10-03 11:30:32.359343",
         "stream": {
            "title": "La Casa Stream",
            "channel_url": "https://www.youtube.com/@somoslacasa"
         },
         "stream_key": "La Casa Stream",
         "live_id": null,
         "live_title": null,
         "last_video_id": "XOzxcMNKCqw",
         "last_video_title": "#CIRCUITOCERRADO | la VERDAD del ECLIPSE | PROGRAMA #17",
         "id": 190282678195799757
      },
      {
         "datetime": "2024-10-03 11:30:32.753998",
         "stream": {
            "title": "Ahora Play",
            "channel_url": "https://www.youtube.com/@tesla1923"
         },
         "stream_key": "Ahora Play",
         "live_id": "smCjzViqJqc",
         "live_title": "¿Cuál será el costo político del veto de Milei? | Reynaldo Sietecase y Pau Macchi #AQuéDarleBola",
         "last_video_id": "R5GyEIG_clE",
         "last_video_title": "MILEI Y EL DESAFÍO DE CONSEGUIR 20 MIL MILLONES DE DÓLARES | Claudio Zlotnik y Carlos Pérez",
         "id": 249666888046518422
      },
      {
         "datetime": "2024-10-03 11:30:33.305176",
         "stream": {
            "title": "Mix On",
            "channel_url": "https://www.youtube.com/@mixontv_"
         },
         "stream_key": "Mix On",
         "live_id": null,
         "live_title": null,
         "last_video_id": "m2WeNN-MY6I",
         "last_video_title": "RAIMUNDI NOS BARDEÓ, EDUCACIÓN PÚBLICA, SI O NO? Y EL AMIGO MUFA | GIRO PERFECTO (02/10)",
         "id": 594791734029866541
      },
      {
         "datetime": "2024-10-03 11:30:33.799249",
         "stream": {
            "title": "Clank!",
            "channel_url": "https://www.youtube.com/@clank_media"
         },
         "stream_key": "Clank!",
         "live_id": null,
         "live_title": null,
         "last_video_id": "Qzday9lVK8E",
         "last_video_title": "Gustavo FERNÁNDEZ con Juan Pablo VARSKY || Clank! Game #48",
         "id": 192085514245794056
      },
      {
         "datetime": "2024-10-03 11:30:34.227203",
         "stream": {
            "title": "YEITE",
            "channel_url": "https://www.youtube.com/@somosyeite"
         },
         "stream_key": "YEITE",
         "live_id": null,
         "live_title": null,
         "last_video_id": "3hojR9s4Q20",
         "last_video_title": "Santi movilero fingió MIAMI por MESSI y las 100 emisiones de YEITE | Finjamos Cordura | YEITE",
         "id": 238851121811026754
      },
      {
         "datetime": "2024-10-03 11:30:34.764731",
         "stream": {
            "title": "Chingon",
            "channel_url": "https://www.youtube.com/@chingonenvivo"
         },
         "stream_key": "Chingon",
         "live_id": "noUnqPMuMb4",
         "live_title": "🔴#PONÉPRIMERA 🟦 CHINGÓN EN VIVO | 03/10🔴",
         "last_video_id": "b8SMal5Es1c",
         "last_video_title": "#ENCENDIDOS I \"HAY QUE DEJAR LA JODA Y SER PADRES JOVENES\" I 2/10",
         "id": 242479339593269520
      },
      {
         "datetime": "2024-10-03 11:30:35.201098",
         "stream": {
            "title": "CEIBO",
            "channel_url": "https://www.youtube.com/@CEIBOARGENTINA"
         },
         "stream_key": "CEIBO",
         "live_id": null,
         "live_title": null,
         "last_video_id": "Q1VQ82Uyskg",
         "last_video_title": "ALDO RICO - COLOQUIO 002",
         "id": 139533723103285548
      },
      {
         "datetime": "2024-10-03 11:30:35.824762",
         "stream": {
            "title": "Brindis TV",
            "channel_url": "https://www.youtube.com/@brindistv"
         },
         "stream_key": "Brindis TV",
         "live_id": null,
         "live_title": null,
         "last_video_id": "v8Y96MCIvyw",
         "last_video_title": "\"TENEMOS LA RESPONSABILIDAD DE ENTREGAR ALEGRÍA\" LOS CALIGARIS EN #PROPINAINCLUIDA",
         "id": 861744236562552074
      },
      {
         "datetime": "2024-10-03 11:30:36.352059",
         "stream": {
            "title": "Laca Stream",
            "channel_url": "https://www.youtube.com/@lacastream"
         },
         "stream_key": "Laca Stream",
         "live_id": null,
         "live_title": null,
         "last_video_id": "OimFCfqbZO8",
         "last_video_title": "TONY COGGI HABLA DE SU SALIDA DEL CANTANDO 2024 | Programa completo #LaCampana - Laca Stream",
         "id": 146186310181938781
      },
      {
         "datetime": "2024-10-03 11:30:36.823480",
         "stream": {
            "title": "Norita Stream",
            "channel_url": "https://www.youtube.com/@NoritaStreaming"
         },
         "stream_key": "Norita Stream",
         "live_id": null,
         "live_title": null,
         "last_video_id": "yTGtk93-z_4",
         "last_video_title": "ENTREVISTA con LEANDRO SANTORO \"El Radical Mas PERONISTA\" | SE SALE POR ARRIBA",
         "id": 321939949179206077
      },
      {
         "datetime": "2024-10-03 11:30:37.232531",
         "stream": {
            "title": "Ziesta TV",
            "channel_url": "https://www.youtube.com/@ZiestaTV"
         },
         "stream_key": "Ziesta TV",
         "live_id": null,
         "live_title": null,
         "last_video_id": "YOaZfo0czFE",
         "last_video_title": "Los pilotos argentinos que corrieron en la Fórmula 1 (min 55:25)",
         "id": 127371374212917847
      },
      {
         "datetime": "2024-10-03 11:30:37.728457",
         "stream": {
            "title": "MOSTRI TV",
            "channel_url": "https://www.youtube.com/@mostritv_"
         },
         "stream_key": "MOSTRI TV",
         "live_id": null,
         "live_title": null,
         "last_video_id": "7gwElL6-Tw8",
         "last_video_title": "EL FUTURO DE LA AFA #NOTICIAS #AFA",
         "id": 234097645604345720
      },
      {
         "datetime": "2024-10-03 11:30:38.150072",
         "stream": {
            "title": "A la Estratosfera",
            "channel_url": "https://www.youtube.com/@estratosferaok"
         },
         "stream_key": "A la Estratosfera",
         "live_id": null,
         "live_title": null,
         "last_video_id": "kGleK73xnyo",
         "last_video_title": "UNIVERSIDAD PÚBLICA con WILLY DURÁN - Decano de Exactas UBA, INTERNA PERONISTA y  TRABAJO con la IA",
         "id": 468647897042064376
      },
      {
         "datetime": "2024-10-03 11:30:38.459587",
         "stream": {
            "title": "Polenta para revolver",
            "channel_url": "https://www.youtube.com/@polentapararevolver"
         },
         "stream_key": "Polenta para revolver",
         "live_id": null,
         "live_title": null,
         "last_video_id": "UROkDtpjjfI",
         "last_video_title": "Pasaron cosas en Jujuy, ninguna buena",
         "id": 510816645398692120
      },
      {
         "datetime": "2024-08-24 22:14:03.514108",
         "stream": {
            "title": "Re FM 107.3",
            "channel_url": "https://www.youtube.com/@ReFM107.3"
         },
         "stream_key": "Re FM 107.3",
         "live_id": null,
         "live_title": null,
         "last_video_id": "D0hoXwIJykc",
         "last_video_title": "GRUPOS ULTRA: LA MÁQUINA DEL ODIO Y LAS FAKE NEWS | Oriane Fléchaire",
         "id": 126855109166765516
      },
      {
         "datetime": "2024-10-03 11:30:38.961358",
         "stream": {
            "title": "Chimi Canal",
            "channel_url": "https://www.youtube.com/@ChimiCanal"
         },
         "stream_key": "Chimi Canal",
         "live_id": null,
         "live_title": null,
         "last_video_id": "Ucqo0Cq6900",
         "last_video_title": "UN JURADO PICANTE en la semana de la hamburguesa que organizó el Circuito Gastronómico",
         "id": 259372155334290277
      },
      {
         "datetime": "2024-10-03 11:30:39.432792",
         "stream": {
            "title": "Diario Alfil Cordoba",
            "channel_url": "https://www.youtube.com/@diario.alfil.cordoba"
         },
         "stream_key": "Diario Alfil Cordoba",
         "live_id": null,
         "live_title": null,
         "last_video_id": "vW2UJYJX238",
         "last_video_title": "ALFIL TV 27 09 24 B04 bloque cultural",
         "id": 288236526587119206
      }
   ]
}