{
   "data": [
      {
         "datetime": "2024-09-12 15:07:48.208337",
         "stream": {
            "title": "Nico Guthmann",
            "channel_url": "https://www.youtube.com/@NicoGuthmann"
         },
         "stream_key": "Nico Guthmann",
         "live_id": "M-pMg9PUhnE",
         "live_title": "MANO A MANO CON MANU JOVE | TUGO EN VIVO con Nico Guthmann",
         "last_video_id": "a6leaUYtqZE",
         "last_video_title": "CÓMO SERÁ el GOBIERNO DE JAVIER MILEI en ARGENTINA",
         "id": 277835498672365003
      },
      {
         "datetime": "2024-09-12 15:07:48.679352",
         "stream": {
            "title": "BLENDER",
            "channel_url": "https://www.youtube.com/@estoesblender"
         },
         "stream_key": "BLENDER",
         "live_id": "jHqgTbeyEyk",
         "live_title": "NAVAJA CRIMEN en ESCUCHO OFERTAS EN VIVO con Guille Aquino y Galia Moldavsky | BLENDER",
         "last_video_id": "uJMXbhBZgzs",
         "last_video_title": "BOB BIG TULA y MEG VICIOUS REVELAN SECRETOS del NOP0R en HAY ALGO AHÍ | BLENDER",
         "id": 533985333570939783
      },
      {
         "datetime": "2024-09-12 15:07:49.289306",
         "stream": {
            "title": "Radio con vos",
            "channel_url": "https://www.youtube.com/@RadioConVos89.9"
         },
         "stream_key": "Radio con vos",
         "live_id": "n48On-kFtpQ",
         "live_title": "LIM con Reynaldo Sietecase | RADIO CON VOS",
         "last_video_id": "0mN4iwDNouo",
         "last_video_title": "Alejandro Rebossio explicó por qué volvió a subir la inflación en agosto",
         "id": 272479996852536616
      },
      {
         "datetime": "2024-09-12 15:07:49.914285",
         "stream": {
            "title": "Gelatina",
            "channel_url": "https://www.youtube.com/@SomosGelatina"
         },
         "stream_key": "Gelatina",
         "live_id": "BNz5i_7imb4",
         "live_title": "ELIJO CREER EN VIVO CON FLOR HALFON | GELATINA",
         "last_video_id": "-3Olr4RqiDQ",
         "last_video_title": "LILIA LEMOINE: LA CAPITANA ANCAP | ARGENTINOS DE BIEN #14 CON VICTORIA DE MASI Y EMILIO LASZLO",
         "id": 259244651430329710
      },
      {
         "datetime": "2024-09-12 15:07:50.413669",
         "stream": {
            "title": "Futurock FM",
            "channel_url": "https://www.youtube.com/@futurock"
         },
         "stream_key": "Futurock FM",
         "live_id": null,
         "live_title": null,
         "last_video_id": "i3y9wMILRs4",
         "last_video_title": "¿QUÉ PELÍCULA ROMÁNTICA SOS? | TEST DE LUCAS con LUCAS ROMÁN en FURIA BEBÉ",
         "id": 233692808435034581
      },
      {
         "datetime": "2024-09-12 15:07:50.927523",
         "stream": {
            "title": "posdata",
            "channel_url": "https://www.youtube.com/@Posdata_ar"
         },
         "stream_key": "posdata",
         "live_id": null,
         "live_title": null,
         "last_video_id": "vC9KfYWPZNU",
         "last_video_title": "GRUPOS de AMIGUES | 3 EMPANADAS | @Posdata_ar",
         "id": 191591078776014768
      },
      {
         "datetime": "2024-09-12 15:07:51.394371",
         "stream": {
            "title": "Cenital",
            "channel_url": "https://www.youtube.com/@Cenitalcom"
         },
         "stream_key": "Cenital",
         "live_id": null,
         "live_title": null,
         "last_video_id": "SCen5XhwbtQ",
         "last_video_title": "EMPRESAS DE COLECTIVOS VS ESTADO: ¿CUÁNTO CUESTA REALMENTE TU BOLETO?",
         "id": 306584204639824864
      },
      {
         "datetime": "2024-09-12 15:07:51.952605",
         "stream": {
            "title": "Factoria 1251",
            "channel_url": "https://www.youtube.com/@factoria1251"
         },
         "stream_key": "Factoria 1251",
         "live_id": null,
         "live_title": null,
         "last_video_id": "zfIDu_G5oWg",
         "last_video_title": "DÍA MUNDIAL para la PREVENCIÓN del SU1CIDIO + INFIDELIDADES / #LoDijeoLoPensé?",
         "id": 185862609823161714
      },
      {
         "datetime": "2024-09-12 15:07:52.418145",
         "stream": {
            "title": "OLGA",
            "channel_url": "https://www.youtube.com/@olgaenvivo_"
         },
         "stream_key": "OLGA",
         "live_id": "E5TYsB7Q1U0",
         "live_title": "SOÑÉ QUE VOLABA en OLGA con Migue Granados, Tefi Russo, Grego Rossello y Lucas Fridman | EN VIVO",
         "last_video_id": "PgEXrs8nN1M",
         "last_video_title": "INTERPELADOS POR EL SALAME | Paraíso Fiscal | COMPLETO 12/9",
         "id": 811783917407851447
      },
      {
         "datetime": "2024-09-12 15:07:53.144752",
         "stream": {
            "title": "LUZU TV",
            "channel_url": "https://www.youtube.com/@luzutv"
         },
         "stream_key": "LUZU TV",
         "live_id": "XGZDbxtwans",
         "live_title": "NADIE DICE NADA con Pollo Alvarez, Yanina Latorre, Santi Talledo y Momi Giardina | EN VIVO",
         "last_video_id": "A29RZ3j-_oE",
         "last_video_title": "#STREAMMASTER l VOLVIÓ EVIL PACHU Y LOS PRIMEROS EN ESCUCHAR EL ALBUM DE CHARLY",
         "id": 125021193912916677
      },
      {
         "datetime": "2024-09-12 15:07:53.583935",
         "stream": {
            "title": "Picnoc Extraterrestre",
            "channel_url": "https://www.youtube.com/@Picnic.Extraterrestre"
         },
         "stream_key": "Picnoc Extraterrestre",
         "live_id": null,
         "live_title": null,
         "last_video_id": "DNpiiT6lymY",
         "last_video_title": "PRIMER FESTIVAL PICNIC EXTRATERRESTRE",
         "id": 748184283104638709
      },
      {
         "datetime": "2024-09-12 15:07:54.047161",
         "stream": {
            "title": "Pais de Boludos",
            "channel_url": "https://www.youtube.com/@PaisDeBoludos"
         },
         "stream_key": "Pais de Boludos",
         "live_id": null,
         "live_title": null,
         "last_video_id": "uD2SRMT6wIM",
         "last_video_title": "PAÍS DE BOLUDOS | LAS FACTURAS DE JAVIER + NATALIA SALVO | PDB",
         "id": 838481804820745772
      },
      {
         "datetime": "2024-09-12 15:07:54.496284",
         "stream": {
            "title": "Peroncho Delivery",
            "channel_url": "https://www.youtube.com/@PeronchoStandUp"
         },
         "stream_key": "Peroncho Delivery",
         "live_id": null,
         "live_title": null,
         "last_video_id": "lw83GfR5OGM",
         "last_video_title": "Oferta de Radicales en el Congreso. Más baratos que argumento libertario.",
         "id": 153341262012569137
      },
      {
         "datetime": "2024-09-12 15:07:55.085542",
         "stream": {
            "title": "Mate",
            "channel_url": "https://www.youtube.com/@somosmatear"
         },
         "stream_key": "Mate",
         "live_id": null,
         "live_title": null,
         "last_video_id": "s8RBYZenr6I",
         "last_video_title": "MACRI DETONA LA LIBERTAD AVANZA, FÓRMULA JUBILATORIA, CRISIS DE LOURDES ARRIETA",
         "id": 145635594759461996
      },
      {
         "datetime": "2024-09-12 15:07:55.637441",
         "stream": {
            "title": "El Destape",
            "channel_url": "https://www.youtube.com/@ElDestapeTV"
         },
         "stream_key": "El Destape",
         "live_id": "dbyh_QxjV1w",
         "live_title": "VERDADES AFILADAS EN VIVO | El Destape",
         "last_video_id": "hjnF0N8mPbw",
         "last_video_title": "MILEI, EL ASESINO DE JUBILADOS | El editorial completo de Roberto Navarro",
         "id": 794690838869899042
      },
      {
         "datetime": "2024-09-12 15:07:56.044391",
         "stream": {
            "title": "Mano a Mano",
            "channel_url": "https://www.youtube.com/@ManoaMano-jz7up"
         },
         "stream_key": "Mano a Mano",
         "live_id": null,
         "live_title": null,
         "last_video_id": "GdAqxht09oo",
         "last_video_title": "CFK, MILEI Y TODO X 2 PESOS. Pablo Ibáñez y Alfredo Zaiat.",
         "id": 294030542011554402
      },
      {
         "datetime": "2024-09-12 15:07:56.421999",
         "stream": {
            "title": "220 Podcast",
            "channel_url": "https://www.youtube.com/@220Podcast"
         },
         "stream_key": "220 Podcast",
         "live_id": null,
         "live_title": null,
         "last_video_id": "dCafTsAgunc",
         "last_video_title": "El AJUSTE DE MILEI, ¿LLEGÓ A UN LÍMITE?",
         "id": 285922738951067278
      },
      {
         "datetime": "2024-09-12 15:07:56.868067",
         "stream": {
            "title": "Eva TV",
            "channel_url": "https://www.youtube.com/@evaenvivo"
         },
         "stream_key": "Eva TV",
         "live_id": null,
         "live_title": null,
         "last_video_id": "XrAWhH2dkBU",
         "last_video_title": "¿TRUMP O HARRIS? ARGENTINO ¿EL INDE? BIEN, GRACIAS | Con la tuia en EVA TV",
         "id": 858554869569070528
      },
      {
         "datetime": "2024-09-12 15:07:57.462326",
         "stream": {
            "title": "Urbana Play",
            "channel_url": "https://www.youtube.com/@UrbanaPlayFM"
         },
         "stream_key": "Urbana Play",
         "live_id": null,
         "live_title": null,
         "last_video_id": "uNpzDweplAM",
         "last_video_title": "Tratan el presupuesto universitario en el Senado y presupuesto 2025: Jairo Straccia #Perros2024",
         "id": 109570434836997627
      },
      {
         "datetime": "2024-09-12 15:07:57.941636",
         "stream": {
            "title": "Bondi Live",
            "channel_url": "https://www.youtube.com/@Bondi_liveok"
         },
         "stream_key": "Bondi Live",
         "live_id": "o0-rqkr7DM0",
         "live_title": "🔴 ÁNGEL RESPONDE con Ángel de Brito, Dalma Maradona, Juli Argenta y Fran Salmain | EN VIVO",
         "last_video_id": "4g9BNbXIldM",
         "last_video_title": "NOS VISITA MIGUEL ANGEL RODRIGUEZ | DESPUES TE EXPLICO 11/9",
         "id": 914347398944020630
      },
      {
         "datetime": "2024-09-12 15:07:58.678887",
         "stream": {
            "title": "Vorterix",
            "channel_url": "https://www.youtube.com/@VorterixOficial"
         },
         "stream_key": "Vorterix",
         "live_id": "2YlNSbnLCA4",
         "live_title": "🔴 ZONA LIBERADA con Marito Baracus y Guillermina Casero | VORTERIX EN VIVO",
         "last_video_id": "kiYb44kTTDY",
         "last_video_title": "BON JOVI EVITÓ UN SUICID10 | #Maldicion | COMPLETO 12/09",
         "id": 215192781492265808
      },
      {
         "datetime": "2024-09-12 15:07:59.123715",
         "stream": {
            "title": "Neura Media",
            "channel_url": "https://www.youtube.com/@NeuraMedia"
         },
         "stream_key": "Neura Media",
         "live_id": "YxTuAvCeNtU",
         "live_title": "Nicolás Promanzio: Letra Chica | !redes !wapp !gumer !remeras",
         "last_video_id": "yinbf1yQZ0I",
         "last_video_title": "Gonzalo Garcés: Partes de la Verdad | Con Andrés Hatum (escritor) y Luciana Vázquez (periodista)",
         "id": 340215558713671423
      },
      {
         "datetime": "2024-09-12 15:07:59.690324",
         "stream": {
            "title": "RepublicaZ",
            "channel_url": "https://www.youtube.com/@republicaz"
         },
         "stream_key": "RepublicaZ",
         "live_id": "MI7IpbtvAaE",
         "live_title": "🔵Republica Z EN VIVO | #LosBros",
         "last_video_id": "aPf0H5L2Od8",
         "last_video_title": "Estamos en Una | ¿CÓMO PREPARARSE para UNA CARRERA DE 42K? + CLASE de YOGA",
         "id": 182946194775217940
      },
      {
         "datetime": "2024-09-12 15:08:00.117331",
         "stream": {
            "title": "La Casa Stream",
            "channel_url": "https://www.youtube.com/@somoslacasa"
         },
         "stream_key": "La Casa Stream",
         "live_id": null,
         "live_title": null,
         "last_video_id": "SLq9dejtQOo",
         "last_video_title": "#CIRCUITOCERRADO | FREESTYLE con MECHA | PROGRAMA #03",
         "id": 190282678195799757
      },
      {
         "datetime": "2024-09-12 15:08:00.459584",
         "stream": {
            "title": "Ahora Play",
            "channel_url": "https://www.youtube.com/@tesla1923"
         },
         "stream_key": "Ahora Play",
         "live_id": null,
         "live_title": null,
         "last_video_id": "KUAa0IP_cRs",
         "last_video_title": "BANCO CENTRAL: LA GRAN APUESTA DEL GOBIERNO PARA QUE LLEGUEN DÓLARES | Maxi Montenegro #AhoraPlay",
         "id": 249666888046518422
      },
      {
         "datetime": "2024-09-12 15:08:00.961070",
         "stream": {
            "title": "Mix On",
            "channel_url": "https://www.youtube.com/@mixontv_"
         },
         "stream_key": "Mix On",
         "live_id": null,
         "live_title": null,
         "last_video_id": "ljEAxiME1jw",
         "last_video_title": "ANÁLISIS DEL PERONISMO ACTUAL, CRISTINA Y LA PELEA DEL AÑO | GIRO PERFECTO (11/09)",
         "id": 594791734029866541
      },
      {
         "datetime": "2024-09-12 15:08:01.388561",
         "stream": {
            "title": "Clank!",
            "channel_url": "https://www.youtube.com/@clank_media"
         },
         "stream_key": "Clank!",
         "live_id": null,
         "live_title": null,
         "last_video_id": "hLj4hr_lV1k",
         "last_video_title": "Derrota de la Argentina ante Colombia",
         "id": 192085514245794056
      },
      {
         "datetime": "2024-09-12 15:08:01.831100",
         "stream": {
            "title": "YEITE",
            "channel_url": "https://www.youtube.com/@somosyeite"
         },
         "stream_key": "YEITE",
         "live_id": null,
         "live_title": null,
         "last_video_id": "fSEQS1wPKHs",
         "last_video_title": "Entrevista con JULIÁN URMAN, autor de los videos con IA \"Riñón Pélvico\" | Club del Plata | YEITE",
         "id": 238851121811026754
      },
      {
         "datetime": "2024-09-12 15:08:02.716548",
         "stream": {
            "title": "Chingon",
            "channel_url": "https://www.youtube.com/@chingonenvivo"
         },
         "stream_key": "Chingon",
         "live_id": "7HAY4LBUp58",
         "live_title": "GPS 🛰️EN VIVO | 12/09",
         "last_video_id": "lROqFAA_trM",
         "last_video_title": "#PONÉPRIMERA I DIPUTADOS RATIFICO EL VETO A LA REFORMA JUBILATORIA I INFLACION DE AGOSTO I 12/09",
         "id": 242479339593269520
      },
      {
         "datetime": "2024-09-12 15:08:03.134997",
         "stream": {
            "title": "CEIBO",
            "channel_url": "https://www.youtube.com/@CEIBOARGENTINA"
         },
         "stream_key": "CEIBO",
         "live_id": null,
         "live_title": null,
         "last_video_id": "aL8Z_1tWS2M",
         "last_video_title": "Bodas de Oro / Vol.3 - Estados Unidos, China y la posición de Argentina.",
         "id": 139533723103285548
      },
      {
         "datetime": "2024-09-12 15:08:03.746175",
         "stream": {
            "title": "Brindis TV",
            "channel_url": "https://www.youtube.com/@brindistv"
         },
         "stream_key": "Brindis TV",
         "live_id": null,
         "live_title": null,
         "last_video_id": "q2IKUseQh34",
         "last_video_title": "FUIMOS AL MARTIN FIERRO y ¿HABLAMOS CON SUSANA?",
         "id": 861744236562552074
      },
      {
         "datetime": "2024-09-12 15:08:04.294190",
         "stream": {
            "title": "Laca Stream",
            "channel_url": "https://www.youtube.com/@lacastream"
         },
         "stream_key": "Laca Stream",
         "live_id": "WjPWwyYI2zk",
         "live_title": "EMMANUEL FERRARIO en LA CASTA con Marcos Shaw, Agus Mauderli y Fede Millenaar | Laca Stream",
         "last_video_id": "AyEznNptcKs",
         "last_video_title": "SE CONFIRMÓ EL VETO A LA LEY DE MOVILIDAD JUBILATORIA | Programa completo #LaCarrera - Laca Stream",
         "id": 146186310181938781
      },
      {
         "datetime": "2024-09-12 15:08:04.777094",
         "stream": {
            "title": "Norita Stream",
            "channel_url": "https://www.youtube.com/@NoritaStreaming"
         },
         "stream_key": "Norita Stream",
         "live_id": null,
         "live_title": null,
         "last_video_id": "zrJfHUWlQRE",
         "last_video_title": "\"VINE EN BICICLETA PORQUE LA PLATA NO ME ALCANZA PARA EL COLECTIVO\"",
         "id": 321939949179206077
      },
      {
         "datetime": "2024-09-12 15:08:05.207501",
         "stream": {
            "title": "Ziesta TV",
            "channel_url": "https://www.youtube.com/@ZiestaTV"
         },
         "stream_key": "Ziesta TV",
         "live_id": "9l72zpkfbgk",
         "live_title": "🔴 ZiestaTV -LA OFI con Mencho, Sandro Pertini y Anto 📊💼 | EN VIVO",
         "last_video_id": "vUZYIEu3LsU",
         "last_video_title": "Consejos para recuperar a tu ex",
         "id": 127371374212917847
      },
      {
         "datetime": "2024-09-12 15:08:05.674737",
         "stream": {
            "title": "MOSTRI TV",
            "channel_url": "https://www.youtube.com/@mostritv_"
         },
         "stream_key": "MOSTRI TV",
         "live_id": null,
         "live_title": null,
         "last_video_id": "q0ysbc6RPeA",
         "last_video_title": "ACUSACIONES CRUZADAS ¿Y AGRESIONES? #TALLERES",
         "id": 234097645604345720
      },
      {
         "datetime": "2024-09-12 15:08:06.102352",
         "stream": {
            "title": "A la Estratosfera",
            "channel_url": "https://www.youtube.com/@estratosferaok"
         },
         "stream_key": "A la Estratosfera",
         "live_id": null,
         "live_title": null,
         "last_video_id": "9BTQjI7O5sA",
         "last_video_title": "PICADITO con AZZARO, el CONFLICTO UNIVERSITARIO y ¿MINUJIN con ANGELINA JOLIE?🫦Argentina Primero #17",
         "id": 468647897042064376
      },
      {
         "datetime": "2024-09-12 15:08:06.401778",
         "stream": {
            "title": "Polenta para revolver",
            "channel_url": "https://www.youtube.com/@polentapararevolver"
         },
         "stream_key": "Polenta para revolver",
         "live_id": null,
         "live_title": null,
         "last_video_id": "UROkDtpjjfI",
         "last_video_title": "Pasaron cosas en Jujuy, ninguna buena",
         "id": 510816645398692120
      },
      {
         "datetime": "2024-08-24 22:14:03.514108",
         "stream": {
            "title": "Re FM 107.3",
            "channel_url": "https://www.youtube.com/@ReFM107.3"
         },
         "stream_key": "Re FM 107.3",
         "live_id": null,
         "live_title": null,
         "last_video_id": "D0hoXwIJykc",
         "last_video_title": "GRUPOS ULTRA: LA MÁQUINA DEL ODIO Y LAS FAKE NEWS | Oriane Fléchaire",
         "id": 126855109166765516
      }
   ]
}