{
   "data": [
      {
         "datetime": "2024-09-18 05:08:56.227212",
         "stream": {
            "title": "Nico Guthmann",
            "channel_url": "https://www.youtube.com/@NicoGuthmann"
         },
         "stream_key": "Nico Guthmann",
         "live_id": null,
         "live_title": null,
         "last_video_id": "a6leaUYtqZE",
         "last_video_title": "CÓMO SERÁ el GOBIERNO DE JAVIER MILEI en ARGENTINA",
         "id": 277835498672365003
      },
      {
         "datetime": "2024-09-18 05:08:56.628503",
         "stream": {
            "title": "BLENDER",
            "channel_url": "https://www.youtube.com/@estoesblender"
         },
         "stream_key": "BLENDER",
         "live_id": null,
         "live_title": null,
         "last_video_id": "lSR-v73gQJU",
         "last_video_title": "PEPE ROSEMBLAT metió UN TOPO en el ASADO de los HÉROES | LA HORA OPERADA | BLENDER",
         "id": 533985333570939783
      },
      {
         "datetime": "2024-09-18 05:08:57.187541",
         "stream": {
            "title": "Radio con vos",
            "channel_url": "https://www.youtube.com/@RadioConVos89.9"
         },
         "stream_key": "Radio con vos",
         "live_id": null,
         "live_title": null,
         "last_video_id": "csYKuN8W0Xg",
         "last_video_title": "Paco Durañona: \"El peronismo es un partido vecinalista del conurbano\" | No Hay Plata",
         "id": 272479996852536616
      },
      {
         "datetime": "2024-09-18 05:08:57.640814",
         "stream": {
            "title": "Gelatina",
            "channel_url": "https://www.youtube.com/@SomosGelatina"
         },
         "stream_key": "Gelatina",
         "live_id": null,
         "live_title": null,
         "last_video_id": "3Qu-9cXWomA",
         "last_video_title": "LA MENTIRA DEL PRESUPUESTO DE MILEI | ALE BARRIOS CON PEDRO ROSEMBLAT",
         "id": 259244651430329710
      },
      {
         "datetime": "2024-09-18 05:08:58.108498",
         "stream": {
            "title": "Futurock FM",
            "channel_url": "https://www.youtube.com/@futurock"
         },
         "stream_key": "Futurock FM",
         "live_id": null,
         "live_title": null,
         "last_video_id": "1bfbKoli7o8",
         "last_video_title": "\"ENCONTRAR A UN NIETO ES HACER UN POCO MÁS JUSTA LA SOCIEDAD\" | JUAN PABLO MOYANO en DDLT",
         "id": 233692808435034581
      },
      {
         "datetime": "2024-09-18 05:08:58.533728",
         "stream": {
            "title": "posdata",
            "channel_url": "https://www.youtube.com/@Posdata_ar"
         },
         "stream_key": "posdata",
         "live_id": null,
         "live_title": null,
         "last_video_id": "vC9KfYWPZNU",
         "last_video_title": "GRUPOS de AMIGUES | 3 EMPANADAS | @Posdata_ar",
         "id": 191591078776014768
      },
      {
         "datetime": "2024-09-18 05:08:58.859639",
         "stream": {
            "title": "Cenital",
            "channel_url": "https://www.youtube.com/@Cenitalcom"
         },
         "stream_key": "Cenital",
         "live_id": null,
         "live_title": null,
         "last_video_id": "Rod1yV9gHEQ",
         "last_video_title": "Roberto Moldavsky con Iván Schargrodsky en #OnTheRecord",
         "id": 306584204639824864
      },
      {
         "datetime": "2024-09-18 05:08:59.425416",
         "stream": {
            "title": "Factoria 1251",
            "channel_url": "https://www.youtube.com/@factoria1251"
         },
         "stream_key": "Factoria 1251",
         "live_id": null,
         "live_title": null,
         "last_video_id": "6Qgd4RlDNkE",
         "last_video_title": "¿QUÉ PASA con la POLÍTICA en la MÚSICA ACTUAL? | CARRITO BOI en #ItiMePreguntó",
         "id": 185862609823161714
      },
      {
         "datetime": "2024-09-18 05:08:59.898443",
         "stream": {
            "title": "OLGA",
            "channel_url": "https://www.youtube.com/@olgaenvivo_"
         },
         "stream_key": "OLGA",
         "live_id": null,
         "live_title": null,
         "last_video_id": "MPyotKqxvIc",
         "last_video_title": "Violencia de género - Julieta Prandi | LA CRUDA #3 con MIGUE GRANADOS",
         "id": 811783917407851447
      },
      {
         "datetime": "2024-09-18 05:09:00.415241",
         "stream": {
            "title": "LUZU TV",
            "channel_url": "https://www.youtube.com/@luzutv"
         },
         "stream_key": "LUZU TV",
         "live_id": null,
         "live_title": null,
         "last_video_id": "fFVhWA-_JgE",
         "last_video_title": "#EDICIONESPECIAL | MICAELA'S, MEJORES AMIGO Y EQUIPO COMPLETO",
         "id": 125021193912916677
      },
      {
         "datetime": "2024-09-18 05:09:00.814694",
         "stream": {
            "title": "Picnoc Extraterrestre",
            "channel_url": "https://www.youtube.com/@Picnic.Extraterrestre"
         },
         "stream_key": "Picnoc Extraterrestre",
         "live_id": null,
         "live_title": null,
         "last_video_id": "R0OAguwGlGI",
         "last_video_title": "FRANCIS MALLMANN CON FABIÁN CASAS | PICNIC EXTRATERRESTRE 13.9 | PROGRAMA COMPLETO",
         "id": 748184283104638709
      },
      {
         "datetime": "2024-09-18 05:09:01.320452",
         "stream": {
            "title": "Pais de Boludos",
            "channel_url": "https://www.youtube.com/@PaisDeBoludos"
         },
         "stream_key": "Pais de Boludos",
         "live_id": null,
         "live_title": null,
         "last_video_id": "Lb_VZ56UnNI",
         "last_video_title": "PAÍS DE BOLUDOS | REPRESIÓN PARA TODA LA FAMILIA + AGUSTÍN ROMBOLÁ | PDB",
         "id": 838481804820745772
      },
      {
         "datetime": "2024-09-18 05:09:01.764476",
         "stream": {
            "title": "Peroncho Delivery",
            "channel_url": "https://www.youtube.com/@PeronchoStandUp"
         },
         "stream_key": "Peroncho Delivery",
         "live_id": null,
         "live_title": null,
         "last_video_id": "UD0xbFaHddw",
         "last_video_title": "Milei cita a Cicerón, ¡Qué Bruto!",
         "id": 153341262012569137
      },
      {
         "datetime": "2024-09-18 05:09:02.286601",
         "stream": {
            "title": "Mate",
            "channel_url": "https://www.youtube.com/@somosmatear"
         },
         "stream_key": "Mate",
         "live_id": null,
         "live_title": null,
         "last_video_id": "s8RBYZenr6I",
         "last_video_title": "MACRI DETONA LA LIBERTAD AVANZA, FÓRMULA JUBILATORIA, CRISIS DE LOURDES ARRIETA",
         "id": 145635594759461996
      },
      {
         "datetime": "2024-09-18 05:09:02.813673",
         "stream": {
            "title": "El Destape",
            "channel_url": "https://www.youtube.com/@ElDestapeTV"
         },
         "stream_key": "El Destape",
         "live_id": null,
         "live_title": null,
         "last_video_id": "lr4R06n2Mq8",
         "last_video_title": "Pasó en serio: Majul culpó a Cristina por el bajo rating de Milei",
         "id": 794690838869899042
      },
      {
         "datetime": "2024-09-18 05:09:03.103401",
         "stream": {
            "title": "Mano a Mano",
            "channel_url": "https://www.youtube.com/@ManoaMano-jz7up"
         },
         "stream_key": "Mano a Mano",
         "live_id": null,
         "live_title": null,
         "last_video_id": "GdAqxht09oo",
         "last_video_title": "CFK, MILEI Y TODO X 2 PESOS. Pablo Ibáñez y Alfredo Zaiat.",
         "id": 294030542011554402
      },
      {
         "datetime": "2024-09-18 05:09:03.418325",
         "stream": {
            "title": "220 Podcast",
            "channel_url": "https://www.youtube.com/@220Podcast"
         },
         "stream_key": "220 Podcast",
         "live_id": null,
         "live_title": null,
         "last_video_id": "4DYRFbGSfRA",
         "last_video_title": "LA INFLACIÓN DEJÓ DE BAJAR, ¿PELIGRA EL PLAN MILEI?",
         "id": 285922738951067278
      },
      {
         "datetime": "2024-09-18 05:09:03.857363",
         "stream": {
            "title": "Eva TV",
            "channel_url": "https://www.youtube.com/@evaenvivo"
         },
         "stream_key": "Eva TV",
         "live_id": null,
         "live_title": null,
         "last_video_id": "CdrXaMa4Zx8",
         "last_video_title": "EL PERONISMO PUEDE Y DEBE GANAR LA CIUDAD | ANDRÉS LA BLUNDA | Re-Actualización doctrinaria EVA TV",
         "id": 858554869569070528
      },
      {
         "datetime": "2024-09-18 05:09:04.434174",
         "stream": {
            "title": "Urbana Play",
            "channel_url": "https://www.youtube.com/@UrbanaPlayFM"
         },
         "stream_key": "Urbana Play",
         "live_id": null,
         "live_title": null,
         "last_video_id": "2Az7jDMiaRY",
         "last_video_title": "Cubrió a su amiga que engaña a su novio con otro del trabajo: chismes que hacen bien #OlvidateDeTodo",
         "id": 109570434836997627
      },
      {
         "datetime": "2024-09-18 05:09:04.901104",
         "stream": {
            "title": "Bondi Live",
            "channel_url": "https://www.youtube.com/@Bondi_liveok"
         },
         "stream_key": "Bondi Live",
         "live_id": null,
         "live_title": null,
         "last_video_id": "yXh5bCsjENY",
         "last_video_title": "LA CRISIS DE \"LOS BROS\" Y LA MODA DE MORE RIAL | EL EEJERCITO DE LA MAÑANA 17/9",
         "id": 914347398944020630
      },
      {
         "datetime": "2024-09-18 05:09:05.428946",
         "stream": {
            "title": "Vorterix",
            "channel_url": "https://www.youtube.com/@VorterixOficial"
         },
         "stream_key": "Vorterix",
         "live_id": null,
         "live_title": null,
         "last_video_id": "hRfSnyUnUcs",
         "last_video_title": "VINO LEILA A BANCAR | #QUÉROMPIMOS Completo - 17/09 | Vorterix",
         "id": 215192781492265808
      },
      {
         "datetime": "2024-09-18 05:09:05.798997",
         "stream": {
            "title": "Neura Media",
            "channel_url": "https://www.youtube.com/@NeuraMedia"
         },
         "stream_key": "Neura Media",
         "live_id": null,
         "live_title": null,
         "last_video_id": "yinbf1yQZ0I",
         "last_video_title": "Gonzalo Garcés: Partes de la Verdad | Con Andrés Hatum (escritor) y Luciana Vázquez (periodista)",
         "id": 340215558713671423
      },
      {
         "datetime": "2024-09-18 05:09:06.252956",
         "stream": {
            "title": "RepublicaZ",
            "channel_url": "https://www.youtube.com/@republicaz"
         },
         "stream_key": "RepublicaZ",
         "live_id": null,
         "live_title": null,
         "last_video_id": "MXghwDczihw",
         "last_video_title": "Menta Granizada | LOS MEJORES BODEGONES de BUENOS AIRES con EL CHICO del CRUNCH + UN NOTI GENIAL",
         "id": 182946194775217940
      },
      {
         "datetime": "2024-09-18 05:09:06.619494",
         "stream": {
            "title": "La Casa Stream",
            "channel_url": "https://www.youtube.com/@somoslacasa"
         },
         "stream_key": "La Casa Stream",
         "live_id": null,
         "live_title": null,
         "last_video_id": "fSjG-xxYOOE",
         "last_video_title": "#CIRCUITOCERRADO | COMPONEMOS el tema EN VIVO | PROGRAMA #06",
         "id": 190282678195799757
      },
      {
         "datetime": "2024-09-18 05:09:06.959923",
         "stream": {
            "title": "Ahora Play",
            "channel_url": "https://www.youtube.com/@tesla1923"
         },
         "stream_key": "Ahora Play",
         "live_id": null,
         "live_title": null,
         "last_video_id": "D37sXshtKO0",
         "last_video_title": "LA APUESTA PARA QUE APAREZCAN LOS DÓLARES Y POR QUÉ DESCONFÍAN DE WALL STREET | Maxi Montenegro",
         "id": 249666888046518422
      },
      {
         "datetime": "2024-09-18 05:09:07.400570",
         "stream": {
            "title": "Mix On",
            "channel_url": "https://www.youtube.com/@mixontv_"
         },
         "stream_key": "Mix On",
         "live_id": null,
         "live_title": null,
         "last_video_id": "uHSbjLwq3ag",
         "last_video_title": "PROGRAMA TOTALMENTE NOSTÁLGICO, MUCHOS DERRAPES Y NADA VA A SER IGUAL | GIRO PERFECTO (17/09)",
         "id": 594791734029866541
      },
      {
         "datetime": "2024-09-18 05:09:07.837656",
         "stream": {
            "title": "Clank!",
            "channel_url": "https://www.youtube.com/@clank_media"
         },
         "stream_key": "Clank!",
         "live_id": null,
         "live_title": null,
         "last_video_id": "Aq-2NQfg1NU",
         "last_video_title": "Lionel SCALONI con Juan Pablo VARSKY || Clank! Game #46",
         "id": 192085514245794056
      },
      {
         "datetime": "2024-09-18 05:09:08.247734",
         "stream": {
            "title": "YEITE",
            "channel_url": "https://www.youtube.com/@somosyeite"
         },
         "stream_key": "YEITE",
         "live_id": null,
         "live_title": null,
         "last_video_id": "m5H_YxtqeLI",
         "last_video_title": "Urbanismo, porteñidad y el Río de la Plata con Esteban Bellotto Kuzminsky | Finjamos Cordura | YEITE",
         "id": 238851121811026754
      },
      {
         "datetime": "2024-09-18 05:09:08.709886",
         "stream": {
            "title": "Chingon",
            "channel_url": "https://www.youtube.com/@chingonenvivo"
         },
         "stream_key": "Chingon",
         "live_id": null,
         "live_title": null,
         "last_video_id": "EifvWIrypoQ",
         "last_video_title": "#LAMESADELFUTBOL I \"CHIQUI\" TAPIA SERÁ PRESIDENTE DE AFA HASTA 2028 I  17/09",
         "id": 242479339593269520
      },
      {
         "datetime": "2024-09-18 05:09:09.036136",
         "stream": {
            "title": "CEIBO",
            "channel_url": "https://www.youtube.com/@CEIBOARGENTINA"
         },
         "stream_key": "CEIBO",
         "live_id": null,
         "live_title": null,
         "last_video_id": "aL8Z_1tWS2M",
         "last_video_title": "Bodas de Oro / Vol.3 - Estados Unidos, China y la posición de Argentina.",
         "id": 139533723103285548
      },
      {
         "datetime": "2024-09-18 05:09:09.582204",
         "stream": {
            "title": "Brindis TV",
            "channel_url": "https://www.youtube.com/@brindistv"
         },
         "stream_key": "Brindis TV",
         "live_id": null,
         "live_title": null,
         "last_video_id": "q2IKUseQh34",
         "last_video_title": "FUIMOS AL MARTIN FIERRO y ¿HABLAMOS CON SUSANA?",
         "id": 861744236562552074
      },
      {
         "datetime": "2024-09-18 05:09:10.001675",
         "stream": {
            "title": "Laca Stream",
            "channel_url": "https://www.youtube.com/@lacastream"
         },
         "stream_key": "Laca Stream",
         "live_id": null,
         "live_title": null,
         "last_video_id": "--_l54uf9Eo",
         "last_video_title": "EL NEGRO ALMEIDA y GERMANA FIGUEROA CASAS en RARO con Tomás Díaz Cueto | Programa completo - Laca",
         "id": 146186310181938781
      },
      {
         "datetime": "2024-09-18 05:09:10.397123",
         "stream": {
            "title": "Norita Stream",
            "channel_url": "https://www.youtube.com/@NoritaStreaming"
         },
         "stream_key": "Norita Stream",
         "live_id": null,
         "live_title": null,
         "last_video_id": "R-PWo4cMxv4",
         "last_video_title": "Documental CONTRA EL OLVIDO, capítulo 8: Hermanos Gómez",
         "id": 321939949179206077
      },
      {
         "datetime": "2024-09-18 05:09:10.764410",
         "stream": {
            "title": "Ziesta TV",
            "channel_url": "https://www.youtube.com/@ZiestaTV"
         },
         "stream_key": "Ziesta TV",
         "live_id": null,
         "live_title": null,
         "last_video_id": "yL1JIwccHQc",
         "last_video_title": "\"Romper la pared\" la serie sobre Ángel Di María (min 8.35)",
         "id": 127371374212917847
      },
      {
         "datetime": "2024-09-18 05:09:11.180594",
         "stream": {
            "title": "MOSTRI TV",
            "channel_url": "https://www.youtube.com/@mostritv_"
         },
         "stream_key": "MOSTRI TV",
         "live_id": null,
         "live_title": null,
         "last_video_id": "q1TgupaKmDA",
         "last_video_title": "UNA Y MEDIA A FAVOR, VARIAS EN CONTRA #NOTICIAS #DNU #MILEI #DOCENTES",
         "id": 234097645604345720
      },
      {
         "datetime": "2024-09-18 05:09:11.581211",
         "stream": {
            "title": "A la Estratosfera",
            "channel_url": "https://www.youtube.com/@estratosferaok"
         },
         "stream_key": "A la Estratosfera",
         "live_id": null,
         "live_title": null,
         "last_video_id": "9BTQjI7O5sA",
         "last_video_title": "PICADITO con AZZARO, el CONFLICTO UNIVERSITARIO y ¿MINUJIN con ANGELINA JOLIE? |Argentina Primero 17",
         "id": 468647897042064376
      },
      {
         "datetime": "2024-09-18 05:09:11.864931",
         "stream": {
            "title": "Polenta para revolver",
            "channel_url": "https://www.youtube.com/@polentapararevolver"
         },
         "stream_key": "Polenta para revolver",
         "live_id": null,
         "live_title": null,
         "last_video_id": "UROkDtpjjfI",
         "last_video_title": "Pasaron cosas en Jujuy, ninguna buena",
         "id": 510816645398692120
      },
      {
         "datetime": "2024-08-24 22:14:03.514108",
         "stream": {
            "title": "Re FM 107.3",
            "channel_url": "https://www.youtube.com/@ReFM107.3"
         },
         "stream_key": "Re FM 107.3",
         "live_id": null,
         "live_title": null,
         "last_video_id": "D0hoXwIJykc",
         "last_video_title": "GRUPOS ULTRA: LA MÁQUINA DEL ODIO Y LAS FAKE NEWS | Oriane Fléchaire",
         "id": 126855109166765516
      },
      {
         "datetime": "2024-09-18 05:09:12.328256",
         "stream": {
            "title": "Chimi Canal",
            "channel_url": "https://www.youtube.com/@ChimiCanal"
         },
         "stream_key": "Chimi Canal",
         "live_id": null,
         "live_title": null,
         "last_video_id": "Nd50WnE485g",
         "last_video_title": "DESMANEJO DEL FUEGO.",
         "id": 259372155334290277
      }
   ]
}