{
   "data": [
      {
         "datetime": "2024-07-19 23:44:30.152241",
         "stream": {
            "title": "Nico Guthmann",
            "channel_url": "https://www.youtube.com/@NicoGuthmann"
         },
         "stream_key": "Nico Guthmann",
         "live_id": null,
         "live_title": null,
         "last_video_id": "a6leaUYtqZE",
         "last_video_title": "CÓMO SERÁ el GOBIERNO DE JAVIER MILEI en ARGENTINA",
         "id": 277835498672365003
      },
      {
         "datetime": "2024-07-19 23:44:30.699290",
         "stream": {
            "title": "BLENDER",
            "channel_url": "https://www.youtube.com/@estoesblender"
         },
         "stream_key": "BLENDER",
         "live_id": "_ANs-zu41Gk",
         "live_title": "DINERO Y AMOR EN VIVO con Marcos Aramburu, Tomás Quintín Palma y Evitta Luna | BLENDER",
         "last_video_id": "h9gJOu_9-z4",
         "last_video_title": "UN GUILLE PARA MI NAVAJA | ESTO ES CINE especial ADRIÁN SUAR | BLENDER",
         "id": 533985333570939783
      },
      {
         "datetime": "2024-07-19 23:44:31.226965",
         "stream": {
            "title": "Radio con vos",
            "channel_url": "https://www.youtube.com/@RadioConVos89.9"
         },
         "stream_key": "Radio con vos",
         "live_id": "4-jGm81X4z0",
         "live_title": "Transmisión en vivo de Radio Con Vos 89.9",
         "last_video_id": "baq1FshzSC4",
         "last_video_title": "María Laura Garrigós de Rébori - Ex interventora del Serv. Penitenciario Fed. | No Dejes Para Mañana",
         "id": 272479996852536616
      },
      {
         "datetime": "2024-07-19 23:44:31.833451",
         "stream": {
            "title": "Gelatina",
            "channel_url": "https://www.youtube.com/@SomosGelatina"
         },
         "stream_key": "Gelatina",
         "live_id": null,
         "live_title": null,
         "last_video_id": "xsA5XeCJfcU",
         "last_video_title": "LOS INFLUENCERS DE MILEI: EL NEGOCIO DEL ODIO | ARGENTINOS DE BIEN #10",
         "id": 259244651430329710
      },
      {
         "datetime": "2024-07-19 23:44:32.522998",
         "stream": {
            "title": "Futurock FM",
            "channel_url": "https://www.youtube.com/@futurock"
         },
         "stream_key": "Futurock FM",
         "live_id": null,
         "live_title": null,
         "last_video_id": "ZE_yaCICuD8",
         "last_video_title": "TAMARA TENENBAUM, JULIANA GATTAS y HUGO MUJICA,  con DARIO SZTAJNSZRAJBER | DEMASIADO HUMANO 2024",
         "id": 233692808435034581
      },
      {
         "datetime": "2024-07-19 23:44:33.032026",
         "stream": {
            "title": "posdata",
            "channel_url": "https://www.youtube.com/@Posdata_ar"
         },
         "stream_key": "posdata",
         "live_id": "OBtC5AIW3zc",
         "live_title": "TRES EMPANADAS con María Sztajnszrajber, Vero Lorca y Sol Despeinada | @Posdata_ar",
         "last_video_id": "yl6sAp6BCwc",
         "last_video_title": "Spoiler Alert con @Teloresumoasinomas | Noticias de Ayer | @Posdata_ar",
         "id": 191591078776014768
      },
      {
         "datetime": "2024-07-19 23:44:33.474916",
         "stream": {
            "title": "Cenital",
            "channel_url": "https://www.youtube.com/@Cenitalcom"
         },
         "stream_key": "Cenital",
         "live_id": null,
         "live_title": null,
         "last_video_id": "WiNpIYK6FEE",
         "last_video_title": "LOS RIESGOS DE LA NUEVA DEUDA DE MILEI | Jairo Straccia en #FallaDeMercado",
         "id": 306584204639824864
      },
      {
         "datetime": "2024-07-19 23:44:34.063181",
         "stream": {
            "title": "Factoria 1251",
            "channel_url": "https://www.youtube.com/@factoria1251"
         },
         "stream_key": "Factoria 1251",
         "live_id": null,
         "live_title": null,
         "last_video_id": "q9xZ-220rW8",
         "last_video_title": "ENTREVISTA con SANTI ADANO / #ItiMePreguntó",
         "id": 185862609823161714
      },
      {
         "datetime": "2024-07-19 23:44:34.590595",
         "stream": {
            "title": "OLGA",
            "channel_url": "https://www.youtube.com/@olgaenvivo_"
         },
         "stream_key": "OLGA",
         "live_id": null,
         "live_title": null,
         "last_video_id": "8lB1vnecUHg",
         "last_video_title": "ESCONDIDAS, EQUITACIÓN VEGANA Y ESTE es MI AMIGO | Soñé que Volaba | COMPLETO 19/7",
         "id": 811783917407851447
      },
      {
         "datetime": "2024-07-19 23:44:35.320918",
         "stream": {
            "title": "LUZU TV",
            "channel_url": "https://www.youtube.com/@luzutv"
         },
         "stream_key": "LUZU TV",
         "live_id": "2KTUS1NLD28",
         "live_title": "🔴 TARDE DE TERTULIA con MARTI BENZA, NICO FERRERO, CAMI JARA Y GIANI | EN VIVO",
         "last_video_id": "YN_Zw2KzCDQ",
         "last_video_title": "#PATRIAYFAMILIA l VOLVIÓ FEDE, AMIGXS CON DERECHOS Y SOFI MORANDI QUEMA A LUQUI",
         "id": 125021193912916677
      },
      {
         "datetime": "2024-07-19 23:44:35.839635",
         "stream": {
            "title": "Picnoc Extraterrestre",
            "channel_url": "https://www.youtube.com/@Picnic.Extraterrestre"
         },
         "stream_key": "Picnoc Extraterrestre",
         "live_id": null,
         "live_title": null,
         "last_video_id": "e5OiklDE_SE",
         "last_video_title": "SANTIAGO MOTORIZADO CON FABIÁN CASAS | PICNIC EXTRATERRESTRE 19.7 | PROGRAMA COMPLETO",
         "id": 748184283104638709
      },
      {
         "datetime": "2024-07-19 23:44:36.314030",
         "stream": {
            "title": "Pais de Boludos",
            "channel_url": "https://www.youtube.com/@PaisDeBoludos"
         },
         "stream_key": "Pais de Boludos",
         "live_id": null,
         "live_title": null,
         "last_video_id": "5ElfJLkFgls",
         "last_video_title": "PAÍS DE BOLUDOS | INDEPENDENCE DAY + JULIO BÁRBARO  | PDB",
         "id": 838481804820745772
      },
      {
         "datetime": "2024-07-19 23:44:36.833734",
         "stream": {
            "title": "Peroncho Delivery",
            "channel_url": "https://www.youtube.com/@PeronchoStandUp"
         },
         "stream_key": "Peroncho Delivery",
         "live_id": null,
         "live_title": null,
         "last_video_id": "-IBbq1F_tIU",
         "last_video_title": "Caputo y Milei van por tus ahorros. ¡Libertarios con la tuya!",
         "id": 153341262012569137
      },
      {
         "datetime": "2024-07-19 23:44:37.461942",
         "stream": {
            "title": "Mate",
            "channel_url": "https://www.youtube.com/@somosmatear"
         },
         "stream_key": "Mate",
         "live_id": "W-p-jPP8oek",
         "live_title": "FE DE A RATOS EP6 | IVANA SZERMAN Y FACU DIAZ | DIA DEL AMIGO CHINAGUS, MIGUEL TAPIA Y DANY ARZUA",
         "last_video_id": "0_6aVXdli80",
         "last_video_title": "¿QUIÉN CONDUCIRÍA EL STREAM DE TU VELORIO? | IDEA MILLONARIA DE IVANA SZERMAN Y FACU DIAZ",
         "id": 145635594759461996
      },
      {
         "datetime": "2024-07-19 23:44:38.092751",
         "stream": {
            "title": "El Destape",
            "channel_url": "https://www.youtube.com/@ElDestapeTV"
         },
         "stream_key": "El Destape",
         "live_id": "ukeEe32PFnM",
         "live_title": "Argentina Política EN VIVO | El Destape",
         "last_video_id": "H3vyiobUcqI",
         "last_video_title": "Otra vez sopa: CAPUTO VENDE TODO EL ORO",
         "id": 794690838869899042
      },
      {
         "datetime": "2024-07-19 23:44:38.480743",
         "stream": {
            "title": "Mano a Mano",
            "channel_url": "https://www.youtube.com/@ManoaMano-jz7up"
         },
         "stream_key": "Mano a Mano",
         "live_id": null,
         "live_title": null,
         "last_video_id": "lTgSpV8r9xI",
         "last_video_title": "Los hermanos Milei y el colapso de la economía. PABLO IBÁÑEZ Y ALFEDO ZAIAT.",
         "id": 294030542011554402
      },
      {
         "datetime": "2024-07-19 23:44:38.913175",
         "stream": {
            "title": "220 Podcast",
            "channel_url": "https://www.youtube.com/@220Podcast"
         },
         "stream_key": "220 Podcast",
         "live_id": null,
         "live_title": null,
         "last_video_id": "24B5Qb1wX14",
         "last_video_title": "¿El PLAN MILEI ESTÁ FRACASANDO?",
         "id": 285922738951067278
      },
      {
         "datetime": "2024-07-19 23:44:39.436833",
         "stream": {
            "title": "Eva TV",
            "channel_url": "https://www.youtube.com/@evaenvivo"
         },
         "stream_key": "Eva TV",
         "live_id": null,
         "live_title": null,
         "last_video_id": "6viFsN-1iNI",
         "last_video_title": "PRESENTE Y FUTURO DEL CINE NACIONAL con EZEQUIEL RADUSKY | Una canta, la otra no en EVA TV",
         "id": 858554869569070528
      },
      {
         "datetime": "2024-07-19 23:44:40.130968",
         "stream": {
            "title": "Urbana Play",
            "channel_url": "https://www.youtube.com/@UrbanaPlayFM"
         },
         "stream_key": "Urbana Play",
         "live_id": null,
         "live_title": null,
         "last_video_id": "NKv-Gsn1nYw",
         "last_video_title": "Una tarde con amigos, las pelis y series para este finde y más #VueltaYMedia",
         "id": 109570434836997627
      }
   ]
}